data_cascade/__init__.py
data_cascade/cascade.py
data_cascade/config.py
data_cascade/fs.py
data_cascade/handlers/__init__.py
data_cascade/handlers/json.py
data_cascade/handlers/registry.py
data_cascade/handlers/toml.py
data_cascade/handlers/yaml.py
data_cascade/io.py
data_cascade/loader.py
data_cascade/logging_utils.py
data_cascade/mapping.py
data_cascade/merge/__init__.py
data_cascade/merge/merge.py
data_cascade/merge/strategy.py
data_cascade/pathops/__init__.py
data_cascade/pathops/access.py
data_cascade/pathops/parse.py
data_cascade/saver.py
data_cascade/traverse.py
data_cascade-0.1.0.dist-info/LICENSE
data_cascade-0.1.0.dist-info/METADATA
data_cascade-0.1.0.dist-info/WHEEL
data_cascade-0.1.0.dist-info/RECORD
