Metadata-Version: 2.3
Name: data-cascade
Version: 0.1.0
Summary: Composable directory-based data cascade loader/saver with per-file origins and a convenient path/proxy API.
License: MIT
Author: Your Name
Author-email: you@example.com
Requires-Python: >=3.10,<4.0
Classifier: License :: OSI Approved :: MIT License
Classifier: Programming Language :: Python :: 3
Classifier: Programming Language :: Python :: 3.10
Classifier: Programming Language :: Python :: 3.11
Classifier: Programming Language :: Python :: 3.12
Classifier: Programming Language :: Python :: 3.13
Provides-Extra: toml
Provides-Extra: yaml
Requires-Dist: PyYAML (>=6.0,<7.0) ; extra == "yaml"
Requires-Dist: ruamel-yaml (>=0.18.0,<0.19.0) ; extra == "yaml"
Requires-Dist: toml (>=0.10.2,<0.11.0) ; extra == "toml"
Requires-Dist: tomli (>=2.0.1,<3.0.0) ; (python_version < "3.11") and (extra == "toml")
Requires-Dist: tomli-w (>=1.0.0,<2.0.0) ; extra == "toml"
Project-URL: Homepage, https://example.com/data-cascade
Project-URL: Repository, https://example.com/data-cascade
